odoo/addons/stock_inventory_valuation_location/README.rst
odoo/addons/stock_inventory_valuation_location/__init__.py
odoo/addons/stock_inventory_valuation_location/__manifest__.py
odoo/addons/stock_inventory_valuation_location/i18n/es.po
odoo/addons/stock_inventory_valuation_location/i18n/es_MX.po
odoo/addons/stock_inventory_valuation_location/i18n/sl.po
odoo/addons/stock_inventory_valuation_location/i18n/stock_inventory_valuation_location.pot
odoo/addons/stock_inventory_valuation_location/models/__init__.py
odoo/addons/stock_inventory_valuation_location/models/stock_quant.py
odoo/addons/stock_inventory_valuation_location/readme/CONTRIBUTORS.rst
odoo/addons/stock_inventory_valuation_location/readme/DESCRIPTION.rst
odoo/addons/stock_inventory_valuation_location/readme/USAGE.rst
odoo/addons/stock_inventory_valuation_location/static/description/icon.png
odoo/addons/stock_inventory_valuation_location/static/description/index.html
odoo/addons/stock_inventory_valuation_location/tests/__init__.py
odoo/addons/stock_inventory_valuation_location/tests/test_stockvaluation.py
odoo/addons/stock_inventory_valuation_location/views/stock_quant_views.xml
odoo12_addon_stock_inventory_valuation_location-12.0.1.0.0.99.dev11.dist-info/METADATA
odoo12_addon_stock_inventory_valuation_location-12.0.1.0.0.99.dev11.dist-info/WHEEL
odoo12_addon_stock_inventory_valuation_location-12.0.1.0.0.99.dev11.dist-info/top_level.txt
odoo12_addon_stock_inventory_valuation_location-12.0.1.0.0.99.dev11.dist-info/RECORD
